handsome/__init__.py
handsome/boy/__init__.py
handsome/boy/message.py
LS_GOAT-0.1.dist-info/METADATA
LS_GOAT-0.1.dist-info/WHEEL
LS_GOAT-0.1.dist-info/top_level.txt
LS_GOAT-0.1.dist-info/RECORD
