Metadata-Version: 2.1
Name: LS-GOAT
Version: 0.1
Summary: 组长：林隆达,组员：沈保双
Author: lld
License: UNKNOWN
Platform: UNKNOWN
